liter/__init__.py
liter/changelog.py
liter/console.py
liter/utils.py
liter/version.py
liter-0.0.3.dist-info/entry_points.txt
liter-0.0.3.dist-info/LICENSE
liter-0.0.3.dist-info/WHEEL
liter-0.0.3.dist-info/METADATA
liter-0.0.3.dist-info/RECORD
