Metadata-Version: 2.1
Name: liter
Version: 0.0.3
Summary: Tool for automating basic python packages task.
License: MIT
Author: Jorge Morgado
Author-email: jorge.morgadov@gmail.com
Requires-Python: >=3.7,<4.0
Classifier: License :: OSI Approved :: MIT License
Classifier: Programming Language :: Python :: 3
Classifier: Programming Language :: Python :: 3.7
Classifier: Programming Language :: Python :: 3.8
Classifier: Programming Language :: Python :: 3.9
Requires-Dist: typer (>=0.3.2,<0.4.0)
